coimbra_chamber/__init__.py
coimbra_chamber/__version__.py
coimbra_chamber/access/experiment/contracts.py
coimbra_chamber/access/experiment/models.py
coimbra_chamber/access/experiment/service.py
coimbra_chamber/engine/analysis/service.py
coimbra_chamber/ifx/configuration.py
coimbra_chamber/manager/data/service.py
coimbra_chamber/tests/__init__.py
coimbra_chamber/tests/conftest.py
coimbra_chamber/tests/access/experiment/exp_acc_integration_test.py
coimbra_chamber/tests/access/experiment/exp_acc_unit_test.py
coimbra_chamber/tests/engine/analysis/anlys_eng_integration_test.py
coimbra_chamber/tests/engine/analysis/anlys_eng_unit_test.py
coimbra_chamber/tests/manager/data/data_mngr_integration_test.py
coimbra_chamber/tests/utility/io/io_util_acceptance_test.py
coimbra_chamber/tests/utility/plot/plt_util_acceptance_test.py
coimbra_chamber/utility/io/contracts.py
coimbra_chamber/utility/io/service.py
coimbra_chamber/utility/plot/contracts.py
coimbra_chamber/utility/plot/service.py
coimbra_chamber-0.0.8.dist-info/LICENSE.txt
coimbra_chamber-0.0.8.dist-info/METADATA
coimbra_chamber-0.0.8.dist-info/WHEEL
coimbra_chamber-0.0.8.dist-info/top_level.txt
coimbra_chamber-0.0.8.dist-info/RECORD
