Metadata-Version: 2.1
Name: coimbra-chamber
Version: 0.0.8
Summary: Python programs for Rich Inman's PhD work involving the Coimbra Chamber at UCSD.
Home-page: https://github.com/rinman24/coimbra_chamber
Author: Rich H. Inman
Author-email: rinman24@gmail.com
License: LICENSE.txt
Platform: UNKNOWN
Classifier: Programming Language :: Python :: 3
Classifier: Programming Language :: Python :: 3.7
Classifier: License :: OSI Approved :: MIT License
Classifier: Operating System :: OS Independent
Requires-Python: >=3.7.0
Requires-Dist: dacite (>=1.0.2)
Requires-Dist: matplotlib (>=3.1.1)
Requires-Dist: mysql-connector-python (>=8.0.17)
Requires-Dist: numpy (>=1.17.1)
Requires-Dist: pandas (>=0.25.1)
Requires-Dist: scipy (>=1.3.1)
Requires-Dist: uncertainties (>=3.1.2)
Requires-Dist: coolprop (>=6.3.0)
Requires-Dist: nptdms (>=0.15.1)
Requires-Dist: sqlalchemy (>=1.3.8)
